{
  "desc": "coq-collections",
  "deps": [ "coq-base" ],
  "pkgs": [
    {
      "pkg_id": [ "Coq", "Lists" ],
      "vo_files": [
        [ "Streams.vo", "ﾔ\u001d雇十u0000ｲ\u0004騾\t們B~" ],
        [ "ListSet.vo", "ﾔ\u001d雇十u0000ｲ\u0004騾\t們B~" ],
        [ "SetoidPermutation.vo", "ﾔ\u001d雇十u0000ｲ\u0004騾\t們B~" ],
        [ "List.vo", "ﾔ\u001d雇十u0000ｲ\u0004騾\t們B~" ],
        [ "SetoidList.vo", "ﾔ\u001d雇十u0000ｲ\u0004騾\t們B~" ],
        [ "ListTactics.vo", "ﾔ\u001d雇十u0000ｲ\u0004騾\t們B~" ],
        [ "StreamMemo.vo", "ﾔ\u001d雇十u0000ｲ\u0004騾\t們B~" ],
        [ "ListDec.vo", "ﾔ\u001d雇十u0000ｲ\u0004騾\t們B~" ]
      ],
      "cma_files": []
    },
    {
      "pkg_id": [ "Coq", "Vectors" ],
      "vo_files": [
        [ "Vector.vo", "ﾔ\u001d雇十u0000ｲ\u0004騾\t們B~" ],
        [ "VectorEq.vo", "ﾔ\u001d雇十u0000ｲ\u0004騾\t們B~" ],
        [ "VectorDef.vo", "ﾔ\u001d雇十u0000ｲ\u0004騾\t們B~" ],
        [ "VectorSpec.vo", "ﾔ\u001d雇十u0000ｲ\u0004騾\t們B~" ],
        [ "Fin.vo", "ﾔ\u001d雇十u0000ｲ\u0004騾\t們B~" ]
      ],
      "cma_files": []
    },
    {
      "pkg_id": [ "Coq", "Sets" ],
      "vo_files": [
        [ "Uniset.vo", "ﾔ\u001d雇十u0000ｲ\u0004騾\t們B~" ],
        [ "Infinite_sets.vo", "ﾔ\u001d雇十u0000ｲ\u0004騾\t們B~" ],
        [ "Ensembles.vo", "ﾔ\u001d雇十u0000ｲ\u0004騾\t們B~" ],
        [ "Classical_sets.vo", "ﾔ\u001d雇十u0000ｲ\u0004騾\t們B~" ],
        [ "Powerset_Classical_facts.vo", "ﾔ\u001d雇十u0000ｲ\u0004騾\t們B~" ],
        [ "Relations_1.vo", "ﾔ\u001d雇十u0000ｲ\u0004騾\t們B~" ],
        [ "Integers.vo", "ﾔ\u001d雇十u0000ｲ\u0004騾\t們B~" ],
        [ "Partial_Order.vo", "ﾔ\u001d雇十u0000ｲ\u0004騾\t們B~" ],
        [ "Permut.vo", "ﾔ\u001d雇十u0000ｲ\u0004騾\t們B~" ],
        [ "Relations_2_facts.vo", "ﾔ\u001d雇十u0000ｲ\u0004騾\t們B~" ],
        [ "Relations_3_facts.vo", "ﾔ\u001d雇十u0000ｲ\u0004騾\t們B~" ],
        [ "Powerset_facts.vo", "ﾔ\u001d雇十u0000ｲ\u0004騾\t們B~" ],
        [ "Finite_sets.vo", "ﾔ\u001d雇十u0000ｲ\u0004騾\t們B~" ],
        [ "Cpo.vo", "ﾔ\u001d雇十u0000ｲ\u0004騾\t們B~" ],
        [ "Relations_3.vo", "ﾔ\u001d雇十u0000ｲ\u0004騾\t們B~" ],
        [ "Relations_2.vo", "ﾔ\u001d雇十u0000ｲ\u0004騾\t們B~" ],
        [ "Finite_sets_facts.vo", "ﾔ\u001d雇十u0000ｲ\u0004騾\t們B~" ],
        [ "Powerset.vo", "ﾔ\u001d雇十u0000ｲ\u0004騾\t們B~" ],
        [ "Constructive_sets.vo", "ﾔ\u001d雇十u0000ｲ\u0004騾\t們B~" ],
        [ "Relations_1_facts.vo", "ﾔ\u001d雇十u0000ｲ\u0004騾\t們B~" ],
        [ "Multiset.vo", "ﾔ\u001d雇十u0000ｲ\u0004騾\t們B~" ],
        [ "Image.vo", "ﾔ\u001d雇十u0000ｲ\u0004騾\t們B~" ]
      ],
      "cma_files": []
    },
    {
      "pkg_id": [ "Coq", "FSets" ],
      "vo_files": [
        [ "FSetDecide.vo", "ﾔ\u001d雇十u0000ｲ\u0004騾\t們B~" ],
        [ "FMaps.vo", "ﾔ\u001d雇十u0000ｲ\u0004騾\t們B~" ],
        [ "FMapFacts.vo", "ﾔ\u001d雇十u0000ｲ\u0004騾\t們B~" ],
        [ "FSetList.vo", "ﾔ\u001d雇十u0000ｲ\u0004騾\t們B~" ],
        [ "FSetFacts.vo", "ﾔ\u001d雇十u0000ｲ\u0004騾\t們B~" ],
        [ "FMapFullAVL.vo", "ﾔ\u001d雇十u0000ｲ\u0004騾\t們B~" ],
        [ "FSetProperties.vo", "ﾔ\u001d雇十u0000ｲ\u0004騾\t們B~" ],
        [ "FSetInterface.vo", "ﾔ\u001d雇十u0000ｲ\u0004騾\t們B~" ],
        [ "FSetWeakList.vo", "ﾔ\u001d雇十u0000ｲ\u0004騾\t們B~" ],
        [ "FMapList.vo", "ﾔ\u001d雇十u0000ｲ\u0004騾\t們B~" ],
        [ "FSetPositive.vo", "ﾔ\u001d雇十u0000ｲ\u0004騾\t們B~" ],
        [ "FSetToFiniteSet.vo", "ﾔ\u001d雇十u0000ｲ\u0004騾\t們B~" ],
        [ "FMapInterface.vo", "ﾔ\u001d雇十u0000ｲ\u0004騾\t們B~" ],
        [ "FMapWeakList.vo", "ﾔ\u001d雇十u0000ｲ\u0004騾\t們B~" ],
        [ "FSetCompat.vo", "ﾔ\u001d雇十u0000ｲ\u0004騾\t們B~" ],
        [ "FMapPositive.vo", "ﾔ\u001d雇十u0000ｲ\u0004騾\t們B~" ],
        [ "FSetEqProperties.vo", "ﾔ\u001d雇十u0000ｲ\u0004騾\t們B~" ],
        [ "FSets.vo", "ﾔ\u001d雇十u0000ｲ\u0004騾\t們B~" ],
        [ "FMapAVL.vo", "ﾔ\u001d雇十u0000ｲ\u0004騾\t們B~" ],
        [ "FSetBridge.vo", "ﾔ\u001d雇十u0000ｲ\u0004騾\t們B~" ],
        [ "FSetAVL.vo", "ﾔ\u001d雇十u0000ｲ\u0004騾\t們B~" ]
      ],
      "cma_files": []
    },
    {
      "pkg_id": [ "Coq", "MSets" ],
      "vo_files": [
        [ "MSets.vo", "ﾔ\u001d雇十u0000ｲ\u0004騾\t們B~" ],
        [ "MSetEqProperties.vo", "ﾔ\u001d雇十u0000ｲ\u0004騾\t們B~" ],
        [ "MSetPositive.vo", "ﾔ\u001d雇十u0000ｲ\u0004騾\t們B~" ],
        [ "MSetWeakList.vo", "ﾔ\u001d雇十u0000ｲ\u0004騾\t們B~" ],
        [ "MSetList.vo", "ﾔ\u001d雇十u0000ｲ\u0004騾\t們B~" ],
        [ "MSetInterface.vo", "ﾔ\u001d雇十u0000ｲ\u0004騾\t們B~" ],
        [ "MSetToFiniteSet.vo", "ﾔ\u001d雇十u0000ｲ\u0004騾\t們B~" ],
        [ "MSetRBT.vo", "ﾔ\u001d雇十u0000ｲ\u0004騾\t們B~" ],
        [ "MSetGenTree.vo", "ﾔ\u001d雇十u0000ｲ\u0004騾\t們B~" ],
        [ "MSetDecide.vo", "ﾔ\u001d雇十u0000ｲ\u0004騾\t們B~" ],
        [ "MSetProperties.vo", "ﾔ\u001d雇十u0000ｲ\u0004騾\t們B~" ],
        [ "MSetAVL.vo", "ﾔ\u001d雇十u0000ｲ\u0004騾\t們B~" ],
        [ "MSetFacts.vo", "ﾔ\u001d雇十u0000ｲ\u0004騾\t們B~" ]
      ],
      "cma_files": []
    },
    {
      "pkg_id": [ "Coq", "Sorting" ],
      "vo_files": [
        [ "PermutEq.vo", "ﾔ\u001d雇十u0000ｲ\u0004騾\t們B~" ],
        [ "Heap.vo", "ﾔ\u001d雇十u0000ｲ\u0004騾\t們B~" ],
        [ "Sorting.vo", "ﾔ\u001d雇十u0000ｲ\u0004騾\t們B~" ],
        [ "PermutSetoid.vo", "ﾔ\u001d雇十u0000ｲ\u0004騾\t們B~" ],
        [ "Permutation.vo", "ﾔ\u001d雇十u0000ｲ\u0004騾\t們B~" ],
        [ "Sorted.vo", "ﾔ\u001d雇十u0000ｲ\u0004騾\t們B~" ],
        [ "Mergesort.vo", "ﾔ\u001d雇十u0000ｲ\u0004騾\t們B~" ]
      ],
      "cma_files": []
    }
  ]
}
